openaleph/__init__.py
openaleph/api.py
openaleph/cli.py
openaleph/crawldir.py
openaleph/errors.py
openaleph/fetchdir.py
openaleph/settings.py
openaleph/util.py
openaleph/tests/__init__.py
openaleph/tests/test_api_collection.py
openaleph/tests/test_api_search.py
openaleph/tests/test_crawldir.py
openaleph/tests/test_tasks.py
openaleph-1.0.1.post1.dist-info/licenses/LICENSE
openaleph-1.0.1.post1.dist-info/METADATA
openaleph-1.0.1.post1.dist-info/WHEEL
openaleph-1.0.1.post1.dist-info/top_level.txt
openaleph-1.0.1.post1.dist-info/RECORD
