Metadata-Version: 2.4
Name: openaleph
Version: 1.0.1.post1
Summary: This project has been renamed. Please install 'openaleph-client'.
Author-email: Data and Research Center - DARC <hi@dataresearchcenter.org>
License: MIT License
Project-URL: Repository, https://github.com/dataresearchcenter/opal-client
Classifier: Programming Language :: Python :: 3
Classifier: License :: OSI Approved :: MIT License
Classifier: Operating System :: OS Independent
Requires-Python: >=3.7
License-File: LICENSE
Requires-Dist: openaleph-client>=1.0.1
Dynamic: license-file
